{"id":"5ee9f900a07cac1a3c56ad21","country":"FR","name":"C\u00f4te de porc dans l'\u00e9chine & salsa verde italienne","seoName":null,"category":{"id":"5bd6f0ef19c55bee469039af","type":"pork","name":"Pork","slug":"pork","iconLink":null,"iconPath":"","usage":0},"slug":"cote-de-porc-dans-lechine-salsa-verde-italienne","headline":"sur tomb\u00e9e d'\u00e9pinards, carottes et haricots blancs","description":".","descriptionHTML":"<p>.<\/p>","descriptionMarkdown":".","seoDescription":null,"comment":"RFR16631775-1","difficulty":2,"prepTime":"PT30M","totalTime":null,"servingSize":473,"createdAt":"2020-06-17T11:05:38+00:00","updatedAt":"2020-09-03T12:18:11+00:00","link":"https:\/\/hellofresh.com\/recipes\/5ee9f900a07cac1a3c56ad21","imageLink":"https:\/\/d3hvwccx09j84u.cloudfront.net\/0,0\/image\/cote-de-porc-dans-lechine-salsa-verde-italienne-2ba6efbb.jpg","imagePath":"\/image\/cote-de-porc-dans-lechine-salsa-verde-italienne-2ba6efbb.jpg","cardLink":null,"videoLink":null,"nutrition":[{"type":"57b42a48b7e8697d4b30530d","name":"\u00c9nergie (kJ)","amount":3241,"unit":"kJ"},{"type":"57b42a48b7e8697d4b305304","name":"\u00c9nergie (kcal)","amount":775,"unit":"kcal"},{"type":"57b42a48b7e8697d4b305307","name":"Mati\u00e8res grasses","amount":64,"unit":"g"},{"type":"57b42a48b7e8697d4b305308","name":"dont acides gras satur\u00e9s","amount":18,"unit":"g"},{"type":"57b42a48b7e8697d4b305305","name":"Glucides","amount":19,"unit":"g"},{"type":"57b42a48b7e8697d4b305306","name":"dont sucres","amount":7,"unit":"g"},{"type":"57b42a48b7e8697d4b305309","name":"Prot\u00e9ines","amount":27,"unit":"g"},{"type":"57b42a48b7e8697d4b30530b","name":"Sel","amount":3,"unit":"g"}],"ingredients":[{"country":"FR","id":"5c8bcd9be3f3397358648c94","type":"qdoc-phf-10-16060-4","name":"\u00c9chalote","slug":"echalote","description":null,"internalName":null,"shipped":true,"imageLink":"https:\/\/d3hvwccx09j84u.cloudfront.net\/200,200\/ingredient\/5c8bcd9be3f3397358648c94-8df3c125.png","imagePath":"\/ingredient\/5c8bcd9be3f3397358648c94-8df3c125.png","usage":843,"hasDuplicatedName":null,"allergens":[],"family":{"id":"58877cf3ed71a76e9c03fbee","type":"onion","description":null,"priority":0,"iconLink":"https:\/\/d3hvwccx09j84u.cloudfront.net\/200,200\/ingredient-families\/58877cf3ed71a76e9c03fbee-34de32d5.png","iconPath":"\/ingredient-families\/58877cf3ed71a76e9c03fbee-34de32d5.png","usageByCountry":{"AO":798,"AT":7252,"AU":3246,"BE":1320,"CA":3295,"CF":21,"CG":0,"CH":3443,"CK":1774,"DE":6471,"DK":22,"ER":2474,"ES":0,"FJ":3533,"FR":1935,"GB":4973,"GN":335,"GQ":15,"IE":0,"IT":7,"JP":160,"LU":2512,"MR":0,"NL":1508,"NO":20,"NZ":2474,"SE":44,"US":6192,"YE":0},"createdAt":"2017-01-24T16:12:35+00:00","updatedAt":"2020-11-19T15:34:32+00:00","uuid":"1a30a8a2-71bc-52c5-89fa-8184b99ce42c","name":"oignon","slug":"oignon"},"uuid":"4a5f6773-9803-5515-8c64-24466b0c2f76"},{"country":"FR","id":"5c8bcd9de3f33973480ec962","type":"qdoc-phf-10-16851-4","name":"Gousse d'ail","slug":"ail-gousse","description":null,"internalName":null,"shipped":true,"imageLink":"https:\/\/d3hvwccx09j84u.cloudfront.net\/200,200\/ingredient\/5c8bcd9de3f33973480ec962-3a8e669d.png","imagePath":"\/ingredient\/5c8bcd9de3f33973480ec962-3a8e669d.png","usage":2665,"hasDuplicatedName":null,"allergens":[],"family":{"id":"58877cf3ed71a76e9c03fba4","type":"garlic","description":null,"priority":0,"iconLink":"https:\/\/d3hvwccx09j84u.cloudfront.net\/200,200\/ingredient-families\/58877cf3ed71a76e9c03fba4-20b617ed.png","iconPath":"\/ingredient-families\/58877cf3ed71a76e9c03fba4-20b617ed.png","usageByCountry":{"AO":1594,"AT":8242,"AU":4207,"BE":4396,"CA":2900,"CF":25,"CG":0,"CH":3910,"CK":995,"DE":7430,"DK":17,"ER":3080,"ES":0,"FJ":3553,"FR":2667,"GB":4993,"GN":850,"GQ":46,"IE":0,"IT":0,"JP":202,"LU":5290,"MR":0,"NL":3862,"NO":11,"NZ":3611,"SE":39,"US":3009,"YE":0},"createdAt":"2017-01-24T16:12:35+00:00","updatedAt":"2020-11-19T15:34:30+00:00","uuid":"73da5048-bc09-5236-add6-6ab34fb3dd6f","name":"ail","slug":"ail"},"uuid":"2a70261c-ee65-514b-9142-7e4e6d9035d9"},{"country":"FR","id":"5c70001ce3f3396c4723f663","type":"remps-phf-11-45825-4","name":"Persil plat, menthe et basilic","slug":"persil-plat-menthe-et-basilic-frais","description":null,"internalName":null,"shipped":true,"imageLink":"https:\/\/d3hvwccx09j84u.cloudfront.net\/200,200\/ingredient\/5c3c5178e3f3391bc5331fb2-93793166.png","imagePath":"\/ingredient\/5c3c5178e3f3391bc5331fb2-93793166.png","usage":4,"hasDuplicatedName":null,"allergens":["57962a07b7e8697d4b3052f3"],"family":{"id":"58877cf3ed71a76e9c03fbf9","type":"parsley","description":null,"priority":0,"iconLink":"https:\/\/d3hvwccx09j84u.cloudfront.net\/200,200\/ingredient-families\/58877cf3ed71a76e9c03fbf9-f38cbfcd.png","iconPath":"\/ingredient-families\/58877cf3ed71a76e9c03fbf9-f38cbfcd.png","usageByCountry":{"AO":58,"AT":4452,"AU":923,"BE":532,"CA":819,"CF":3,"CG":0,"CH":1914,"CK":145,"DE":3557,"DK":912,"ER":148,"ES":0,"FJ":787,"FR":674,"GB":1149,"GN":326,"GQ":18,"IE":0,"IT":0,"JP":0,"LU":1730,"MR":0,"NL":753,"NO":917,"NZ":537,"SE":937,"US":548,"YE":0},"createdAt":"2017-01-24T16:12:35+00:00","updatedAt":"2020-11-19T15:34:33+00:00","uuid":"813844a6-db58-5081-94e0-8cfb0e7c5a9b","name":"persil","slug":"persil"},"uuid":"96ff7e9d-4878-5d5e-9bed-f6e93012b149"},{"country":"FR","id":"5af2be04ae08b5194415a151","type":"QDOC-PRO-10-13175-4","name":"C\u00e2pres","slug":"capres","description":null,"internalName":"","shipped":true,"imageLink":"https:\/\/d3hvwccx09j84u.cloudfront.net\/200,200\/ingredients\/56ab62b0fd2cb9da028b4568-a2f76957.png","imagePath":"\/ingredients\/56ab62b0fd2cb9da028b4568-a2f76957.png","usage":69,"hasDuplicatedName":null,"allergens":[],"family":null,"uuid":"ca666667-b157-53a5-bdcf-aef9e90640fa"},{"country":"FR","id":"5c950d77c445fa28926e8832","type":"qdoc-phf-10-16721-4","name":"Citron jaune","slug":"citron","description":null,"internalName":null,"shipped":true,"imageLink":"https:\/\/d3hvwccx09j84u.cloudfront.net\/200,200\/ingredient\/5c950d77c445fa28926e8832-ae27442b.png","imagePath":"\/ingredient\/5c950d77c445fa28926e8832-ae27442b.png","usage":652,"hasDuplicatedName":null,"allergens":[],"family":{"id":"58877cf3ed71a76e9c03fbc5","type":"lemon","description":null,"priority":0,"iconLink":"https:\/\/d3hvwccx09j84u.cloudfront.net\/200,200\/ingredient-families\/58877cf3ed71a76e9c03fbc5-ae27442b.png","iconPath":"\/ingredient-families\/58877cf3ed71a76e9c03fbc5-ae27442b.png","usageByCountry":{"AO":201,"AT":2226,"AU":1461,"BE":881,"CA":875,"CF":7,"CG":0,"CH":937,"CK":299,"DE":2002,"DK":507,"ER":745,"ES":0,"FJ":369,"FR":677,"GB":1075,"GN":227,"GQ":19,"IE":0,"IT":0,"JP":53,"LU":1038,"MR":0,"NL":999,"NO":42,"NZ":1055,"SE":539,"US":2168,"YE":0},"createdAt":"2017-01-24T16:12:35+00:00","updatedAt":"2020-11-19T15:34:31+00:00","uuid":"3f3c3cbb-7960-5dcd-be95-cdb72d76e1a1","name":"citron","slug":"citron"},"uuid":"f726152b-cf71-5275-b4ad-8d1cd402ff98"},{"country":"FR","id":"5bdc60dbae08b57bc06363d5","type":"qdoc-ptn-10-47026-4","name":"\u00c9chine de porc d\u00e9soss\u00e9e","slug":"echine-de-porc-desossee","description":null,"internalName":null,"shipped":true,"imageLink":"https:\/\/d3hvwccx09j84u.cloudfront.net\/200,200\/ingredient\/5bdc60dbae08b57bc06363d5-3549582c.png","imagePath":"\/ingredient\/5bdc60dbae08b57bc06363d5-3549582c.png","usage":18,"hasDuplicatedName":null,"allergens":[],"family":{"id":"58877cf3ed71a76e9c03fc12","type":"pork","description":null,"priority":0,"iconLink":"https:\/\/d3hvwccx09j84u.cloudfront.net\/200,200\/ingredient-families\/58877cf3ed71a76e9c03fc12-bdd443ff.png","iconPath":"\/ingredient-families\/58877cf3ed71a76e9c03fc12-bdd443ff.png","usageByCountry":{"AO":323,"AT":3026,"AU":1051,"BE":131,"CA":712,"CF":3,"CG":0,"CH":1188,"CK":349,"DE":2119,"DK":498,"ER":696,"ES":0,"FJ":387,"FR":169,"GB":1644,"GN":79,"GQ":3,"IE":0,"IT":23,"JP":77,"LU":274,"MR":0,"NL":213,"NO":564,"NZ":873,"SE":424,"US":1637,"YE":0},"createdAt":"2017-01-24T16:12:35+00:00","updatedAt":"2020-11-19T15:34:33+00:00","uuid":"bbc3a600-642a-5eeb-9af1-c77ca2ee2317","name":"porc","slug":"porc"},"uuid":"0c4b5d75-44ea-55e5-8d3b-391d7f810b30"},{"country":"FR","id":"5af2be68ae08b5194415a2c0","type":"qdoc-phf-10-16950-4","name":"Carotte","slug":"carotte","description":null,"internalName":null,"shipped":true,"imageLink":"https:\/\/d3hvwccx09j84u.cloudfront.net\/200,200\/ingredient\/5af2be68ae08b5194415a2c0-3e32691c.png","imagePath":"\/ingredient\/5af2be68ae08b5194415a2c0-3e32691c.png","usage":629,"hasDuplicatedName":null,"allergens":[],"family":{"id":"58877cf3ed71a76e9c03fb62","type":"carrot","description":null,"priority":0,"iconLink":"https:\/\/d3hvwccx09j84u.cloudfront.net\/200,200\/ingredient-families\/58877cf3ed71a76e9c03fb62-c4a1f62d.png","iconPath":"\/ingredient-families\/58877cf3ed71a76e9c03fb62-c4a1f62d.png","usageByCountry":{"AO":1164,"AT":3504,"AU":2719,"BE":918,"CA":591,"CF":1,"CG":0,"CH":1703,"CK":373,"DE":3105,"DK":29,"ER":556,"ES":0,"FJ":194,"FR":747,"GB":1174,"GN":190,"GQ":7,"IE":0,"IT":0,"JP":50,"LU":1080,"MR":0,"NL":861,"NO":24,"NZ":2475,"SE":44,"US":1213,"YE":14},"createdAt":"2017-01-24T16:12:35+00:00","updatedAt":"2020-11-19T15:34:30+00:00","uuid":"b183506b-ae5e-5689-9362-9c74e6f64079","name":"carotte","slug":"carotte"},"uuid":"2c4be4cd-cdcd-5628-bcb4-becf6d42b039"},{"country":"FR","id":"5bceef3a30006c2b0d5d7232","type":"QDOC-PRO-10-47947-4","name":"Haricots blancs","slug":"haricots-blancs","description":null,"internalName":"","shipped":true,"imageLink":"https:\/\/d3hvwccx09j84u.cloudfront.net\/200,200\/ingredient\/59fb3291a1e1ea1dbc351824-cac32064.png","imagePath":"\/ingredient\/59fb3291a1e1ea1dbc351824-cac32064.png","usage":49,"hasDuplicatedName":null,"allergens":[],"family":null,"uuid":"2ea21098-00a0-5464-b535-5ebcb6eb82bb"},{"country":"FR","id":"5af2be60ae08b5194415a2a2","type":"QDOC-PHF-10-16077-4","name":"\u00c9pinards","slug":"epinards","description":null,"internalName":"","shipped":true,"imageLink":"https:\/\/d3hvwccx09j84u.cloudfront.net\/200,200\/image\/554a53a4f8b25e1c268b456e.png","imagePath":"\/image\/554a53a4f8b25e1c268b456e.png","usage":401,"hasDuplicatedName":null,"allergens":["57962a07b7e8697d4b3052f3"],"family":null,"uuid":"57a12037-b35c-5236-a06b-982e4aad7fd7"},{"country":"FR","id":"5ca75c90e3f339258a36e9f2","type":"zt-extra-vierge-olijfolie","name":"Huile d'olive vierge extra","slug":"huile-d-olive-extra-vierge","description":null,"internalName":"Huile d'olive vierge extra","shipped":false,"imageLink":"https:\/\/d3hvwccx09j84u.cloudfront.net\/200,200\/ingredient\/5ca75c90e3f339258a36e9f2-2e1bc6b6.png","imagePath":"\/ingredient\/5ca75c90e3f339258a36e9f2-2e1bc6b6.png","usage":1099,"hasDuplicatedName":null,"allergens":[],"family":{"id":"58877cf3ed71a76e9c03fbe8","type":"oil","description":null,"priority":0,"iconLink":"https:\/\/d3hvwccx09j84u.cloudfront.net\/200,200\/ingredient-families\/58877cf3ed71a76e9c03fbe8-34c502d3.png","iconPath":"\/ingredient-families\/58877cf3ed71a76e9c03fbe8-34c502d3.png","usageByCountry":{"AO":0,"AT":14263,"AU":244,"BE":4310,"CA":5128,"CF":0,"CG":0,"CH":7014,"CK":2457,"DE":12535,"DK":39,"ER":3119,"ES":0,"FJ":108,"FR":1814,"GB":692,"GN":1,"GQ":47,"IE":0,"IT":0,"JP":68,"LU":6546,"MR":0,"NL":4975,"NO":40,"NZ":38,"SE":44,"US":4924,"YE":0},"createdAt":"2017-01-24T16:12:35+00:00","updatedAt":"2020-11-19T15:34:32+00:00","uuid":"40e34e55-5e6b-5d7d-bc35-bf898efa8c03","name":"huile","slug":"huile"},"uuid":"a36b3941-dd55-5a83-b575-bc270f878041"},{"country":"FR","id":"5c8bcd9be3f3397358648c92","type":"zt-olijfolie","name":"Huile d'olive","slug":"huile-d-olive","description":null,"internalName":null,"shipped":false,"imageLink":"https:\/\/d3hvwccx09j84u.cloudfront.net\/200,200\/ingredient\/5c8bcd9be3f3397358648c92-2e1bc6b6.png","imagePath":"\/ingredient\/5c8bcd9be3f3397358648c92-2e1bc6b6.png","usage":3165,"hasDuplicatedName":null,"allergens":[],"family":{"id":"58877cf3ed71a76e9c03fbeb","type":"olive-oil","description":null,"priority":0,"iconLink":"https:\/\/d3hvwccx09j84u.cloudfront.net\/200,200\/ingredient-families\/58877cf3ed71a76e9c03fbeb-2e1bc6b6.png","iconPath":"\/ingredient-families\/58877cf3ed71a76e9c03fbeb-2e1bc6b6.png","usageByCountry":{"AO":2352,"AT":391,"AU":6771,"BE":5214,"CA":3,"CF":0,"CG":0,"CH":66,"CK":0,"DE":359,"DK":1899,"ER":991,"ES":0,"FJ":0,"FR":3179,"GB":1327,"GN":167,"GQ":89,"IE":0,"IT":923,"JP":163,"LU":6658,"MR":0,"NL":6208,"NO":1899,"NZ":5445,"SE":1916,"US":4901,"YE":0},"createdAt":"2017-01-24T16:12:35+00:00","updatedAt":"2020-11-19T15:34:32+00:00","uuid":"7c98f5ea-c7e6-530f-a8f7-837099e95a74","name":"huile","slug":"huile"},"uuid":"9ee0d86f-1a50-54cc-9108-8ac7ea81a416"},{"country":"FR","id":"5c8bcd9ce3f3397358648c95","type":"zt-roomboter","name":"Beurre","slug":"beurre-non-sale","description":null,"internalName":null,"shipped":false,"imageLink":"https:\/\/d3hvwccx09j84u.cloudfront.net\/200,200\/ingredient\/5c8bcd9ce3f3397358648c95-9d60c002.png","imagePath":"\/ingredient\/5c8bcd9ce3f3397358648c95-9d60c002.png","usage":1714,"hasDuplicatedName":null,"allergens":["57962a07b7e8697d4b3052fa"],"family":{"id":"58877cf3ed71a76e9c03fb5b","type":"butter","description":null,"priority":0,"iconLink":"https:\/\/d3hvwccx09j84u.cloudfront.net\/200,200\/ingredient-families\/58877cf3ed71a76e9c03fb5b-10d0b09a.png","iconPath":"\/ingredient-families\/58877cf3ed71a76e9c03fb5b-10d0b09a.png","usageByCountry":{"AO":1385,"AT":3040,"AU":2584,"BE":3342,"CA":1799,"CF":5,"CG":0,"CH":1348,"CK":1194,"DE":2778,"DK":1117,"ER":3019,"ES":0,"FJ":969,"FR":1838,"GB":650,"GN":149,"GQ":25,"IE":0,"IT":0,"JP":62,"LU":4936,"MR":0,"NL":3874,"NO":1112,"NZ":2589,"SE":1125,"US":5244,"YE":0},"createdAt":"2017-01-24T16:12:35+00:00","updatedAt":"2020-11-19T15:34:30+00:00","uuid":"e1a21c36-6c62-5638-9364-d39039f0b218","name":"beurre","slug":"beurre"},"uuid":"19d86b63-a223-5129-8979-a429c1d5d94a"},{"country":"FR","id":"5c8bcdafe3f3397358648c99","type":"kippen-of-groentebouillon","name":"Bouillon de volaille ou de l\u00e9gumes","slug":"kippen-of-groentebouillon","description":null,"internalName":null,"shipped":false,"imageLink":"https:\/\/d3hvwccx09j84u.cloudfront.net\/200,200\/ingredient\/5c8bcdafe3f3397358648c99-2c27cd6e.png","imagePath":"\/ingredient\/5c8bcdafe3f3397358648c99-2c27cd6e.png","usage":80,"hasDuplicatedName":null,"allergens":[],"family":{"id":"58877cf3ed71a76e9c03fb57","type":"broth","description":null,"priority":0,"iconLink":"https:\/\/d3hvwccx09j84u.cloudfront.net\/200,200\/ingredient-families\/58877cf3ed71a76e9c03fb57-6d9f9ef5.png","iconPath":"\/ingredient-families\/58877cf3ed71a76e9c03fb57-6d9f9ef5.png","usageByCountry":{"AO":0,"AT":5177,"AU":0,"BE":42,"CA":35,"CF":0,"CG":0,"CH":1600,"CK":1,"DE":3997,"DK":0,"ER":0,"ES":0,"FJ":0,"FR":91,"GB":84,"GN":39,"GQ":0,"IE":0,"IT":39,"JP":54,"LU":3055,"MR":0,"NL":10,"NO":0,"NZ":0,"SE":398,"US":0,"YE":0},"createdAt":"2017-01-24T16:12:35+00:00","updatedAt":"2020-11-19T15:34:30+00:00","uuid":"7ef4529c-c210-5d1f-a7cd-faf3d412cd15","name":"concentr\u00e9 de stock","slug":"concentr\u00e9-de-stock"},"uuid":"455deaba-f61c-5e2b-86f1-8bab756a44c0"},{"country":"FR","id":"5c8bcd9be3f3397358648c93","type":"zt-peper-en-zout","name":"Poivre et sel","slug":"poivre-et-sel","description":null,"internalName":null,"shipped":false,"imageLink":"https:\/\/d3hvwccx09j84u.cloudfront.net\/200,200\/ingredient\/5c8bcd9be3f3397358648c93-5eaccae0.png","imagePath":"\/ingredient\/5c8bcd9be3f3397358648c93-5eaccae0.png","usage":4221,"hasDuplicatedName":null,"allergens":[],"family":{"id":"58877cf3ed71a76e9c03fc07","type":"pepper-and-salt","description":null,"priority":0,"iconLink":"https:\/\/d3hvwccx09j84u.cloudfront.net\/200,200\/ingredient-families\/58877cf3ed71a76e9c03fc07-5eaccae0.png","iconPath":"\/ingredient-families\/58877cf3ed71a76e9c03fc07-5eaccae0.png","usageByCountry":{"AO":0,"AT":3,"AU":0,"BE":7615,"CA":1954,"CF":0,"CG":0,"CH":0,"CK":1082,"DE":3,"DK":0,"ER":0,"ES":0,"FJ":0,"FR":4221,"GB":0,"GN":0,"GQ":101,"IE":0,"IT":0,"JP":0,"LU":11226,"MR":0,"NL":8879,"NO":0,"NZ":0,"SE":5,"US":0,"YE":0},"createdAt":"2017-01-24T16:12:35+00:00","updatedAt":"2020-11-19T15:34:33+00:00","uuid":"69206917-2dbb-543a-ba93-948b536854a2","name":"m\u00e9lange d'\u00e9pices","slug":"m\u00e9lange-d'\u00e9pices"},"uuid":"4de65d0b-719b-5234-bf46-16082d9985ff"}],"allergens":[{"id":"57962a07b7e8697d4b3052fa","type":"milk","description":null,"tracesOf":false,"triggersTracesOf":false,"iconLink":"https:\/\/d3hvwccx09j84u.cloudfront.net\/0,0\/allergens\/57962a07b7e8697d4b3052fa-be127d3f.png","iconPath":"\/allergens\/57962a07b7e8697d4b3052fa-be127d3f.png","usage":3808,"name":"Lait (dont lactose)","slug":"lait-lactose"},{"id":"57962a07b7e8697d4b3052f3","type":"maycontaintracesofallergens","description":null,"tracesOf":false,"triggersTracesOf":true,"iconLink":null,"iconPath":null,"usage":3911,"name":"Peut contenir des traces d'allerg\u00e8nes","slug":"peut-contenir-des-traces-dallergenes"}],"utensils":[{"id":"57e2674fb7e8697d4b305369","type":"bowl","name":"Bol"},{"id":"57e2674fb7e8697d4b305380","type":"smallbowl","name":"Petit bol"},{"id":"57e2674fb7e8697d4b305366","type":"aluminumfoil","name":"Papier aluminium"},{"id":"57e2674fb7e8697d4b305389","type":"casserole-lid","name":"Sauteuse avec couvercle"},{"id":"57e2674fb7e8697d4b305379","type":"peeler","name":"\u00c9plucheur"}],"tags":[{"id":"57d13370b7e8697d4b305314","type":"eat-me-first","iconLink":"https:\/\/d3hvwccx09j84u.cloudfront.net\/200,200\/tags\/eat-me-first%403x.png","iconPath":"\/tags\/eat-me-first%403x.png","numberOfRecipes":6692,"numberOfRecipesByCountry":{"AO":1,"AT":377,"AU":71,"BE":1093,"CA":46,"CF":0,"CG":0,"CH":121,"CK":0,"DE":303,"DK":0,"ER":0,"ES":0,"FJ":0,"FR":1218,"GB":37,"GN":0,"GQ":0,"IE":0,"IT":0,"JP":0,"LU":1972,"MR":0,"NL":1347,"NO":0,"NZ":3,"SE":0,"US":103,"YE":0},"colorHandle":null,"preferences":[],"name":"\u00e0 manger rapidement","slug":"eat-me-first","displayLabel":true},{"id":"5efb7686bd5c0d38b0058739","type":"family-friendly","iconLink":null,"iconPath":null,"numberOfRecipes":14287,"numberOfRecipesByCountry":{"AO":0,"AT":266,"AU":878,"BE":1088,"CA":989,"CF":0,"CG":0,"CH":311,"CK":0,"DE":239,"DK":1038,"ER":4,"ES":0,"FJ":0,"FR":1337,"GB":1013,"GN":0,"GQ":0,"IE":0,"IT":8,"JP":37,"LU":2250,"MR":0,"NL":1469,"NO":1033,"NZ":838,"SE":1044,"US":445,"YE":0},"colorHandle":"familyFriendly","preferences":["Famille"],"name":"Familiale","slug":"family-friendly","displayLabel":true}],"cuisines":[{"id":"57ebbc17b7e8697d4b3053ac","type":"italian","iconLink":"https:\/\/d3hvwccx09j84u.cloudfront.net\/0,0\/cuisines\/57ebbc17b7e8697d4b3053ac-ed3b5276.jpg","iconPath":"\/cuisines\/57ebbc17b7e8697d4b3053ac-ed3b5276.jpg","usage":22850,"name":"Italienne","slug":"italian"}],"yields":[{"yields":1,"ingredients":[{"id":"5c8bcd9be3f3397358648c94","amount":0.5,"unit":"pi\u00e8ce"},{"id":"5c8bcd9de3f33973480ec962","amount":0.5,"unit":"pi\u00e8ce"},{"id":"5c70001ce3f3396c4723f663","amount":5,"unit":"g"},{"id":"5af2be04ae08b5194415a151","amount":10,"unit":"g"},{"id":"5c950d77c445fa28926e8832","amount":0.5,"unit":"pi\u00e8ce"},{"id":"5bdc60dbae08b57bc06363d5","amount":1,"unit":"pi\u00e8ce"},{"id":"5af2be68ae08b5194415a2c0","amount":0.5,"unit":"pi\u00e8ce"},{"id":"5bceef3a30006c2b0d5d7232","amount":0.25,"unit":"bo\u00eete(s)"},{"id":"5af2be60ae08b5194415a2a2","amount":100,"unit":"g"},{"id":"5ca75c90e3f339258a36e9f2","amount":2,"unit":"cs"},{"id":"5c8bcd9be3f3397358648c92","amount":0.5,"unit":"cs"},{"id":"5c8bcd9ce3f3397358648c95","amount":0.5,"unit":"cs"},{"id":"5c8bcdafe3f3397358648c99","amount":50,"unit":"ml"},{"id":"5c8bcd9be3f3397358648c93","amount":null,"unit":"selon le go\u00fbt"}]},{"yields":2,"ingredients":[{"id":"5c8bcd9be3f3397358648c94","amount":1,"unit":"pi\u00e8ce"},{"id":"5c8bcd9de3f33973480ec962","amount":1,"unit":"pi\u00e8ce"},{"id":"5c70001ce3f3396c4723f663","amount":10,"unit":"g"},{"id":"5af2be04ae08b5194415a151","amount":20,"unit":"g"},{"id":"5c950d77c445fa28926e8832","amount":1,"unit":"pi\u00e8ce"},{"id":"5bdc60dbae08b57bc06363d5","amount":2,"unit":"pi\u00e8ce"},{"id":"5af2be68ae08b5194415a2c0","amount":1,"unit":"pi\u00e8ce"},{"id":"5bceef3a30006c2b0d5d7232","amount":0.5,"unit":"bo\u00eete(s)"},{"id":"5af2be60ae08b5194415a2a2","amount":200,"unit":"g"},{"id":"5ca75c90e3f339258a36e9f2","amount":4,"unit":"cs"},{"id":"5c8bcd9be3f3397358648c92","amount":1,"unit":"cs"},{"id":"5c8bcd9ce3f3397358648c95","amount":1,"unit":"cs"},{"id":"5c8bcdafe3f3397358648c99","amount":100,"unit":"ml"},{"id":"5c8bcd9be3f3397358648c93","amount":null,"unit":"selon le go\u00fbt"}]},{"yields":3,"ingredients":[{"id":"5c8bcd9be3f3397358648c94","amount":1.5,"unit":"pi\u00e8ce"},{"id":"5c8bcd9de3f33973480ec962","amount":1.5,"unit":"pi\u00e8ce"},{"id":"5c70001ce3f3396c4723f663","amount":15,"unit":"g"},{"id":"5af2be04ae08b5194415a151","amount":30,"unit":"g"},{"id":"5c950d77c445fa28926e8832","amount":1.5,"unit":"pi\u00e8ce"},{"id":"5bdc60dbae08b57bc06363d5","amount":3,"unit":"pi\u00e8ce"},{"id":"5af2be68ae08b5194415a2c0","amount":1.5,"unit":"pi\u00e8ce"},{"id":"5bceef3a30006c2b0d5d7232","amount":0.75,"unit":"bo\u00eete(s)"},{"id":"5af2be60ae08b5194415a2a2","amount":300,"unit":"g"},{"id":"5ca75c90e3f339258a36e9f2","amount":6,"unit":"cs"},{"id":"5c8bcd9be3f3397358648c92","amount":1.5,"unit":"cs"},{"id":"5c8bcd9ce3f3397358648c95","amount":1.5,"unit":"cs"},{"id":"5c8bcdafe3f3397358648c99","amount":150,"unit":"ml"},{"id":"5c8bcd9be3f3397358648c93","amount":null,"unit":"selon le go\u00fbt"}]},{"yields":4,"ingredients":[{"id":"5c8bcd9be3f3397358648c94","amount":2,"unit":"pi\u00e8ce"},{"id":"5c8bcd9de3f33973480ec962","amount":2,"unit":"pi\u00e8ce"},{"id":"5c70001ce3f3396c4723f663","amount":20,"unit":"g"},{"id":"5af2be04ae08b5194415a151","amount":40,"unit":"g"},{"id":"5c950d77c445fa28926e8832","amount":2,"unit":"pi\u00e8ce"},{"id":"5bdc60dbae08b57bc06363d5","amount":4,"unit":"pi\u00e8ce"},{"id":"5af2be68ae08b5194415a2c0","amount":2,"unit":"pi\u00e8ce"},{"id":"5bceef3a30006c2b0d5d7232","amount":1,"unit":"bo\u00eete(s)"},{"id":"5af2be60ae08b5194415a2a2","amount":400,"unit":"g"},{"id":"5ca75c90e3f339258a36e9f2","amount":8,"unit":"cs"},{"id":"5c8bcd9be3f3397358648c92","amount":2,"unit":"cs"},{"id":"5c8bcd9ce3f3397358648c95","amount":2,"unit":"cs"},{"id":"5c8bcdafe3f3397358648c99","amount":200,"unit":"ml"},{"id":"5c8bcd9be3f3397358648c93","amount":null,"unit":"selon le go\u00fbt"}]},{"yields":5,"ingredients":[{"id":"5c8bcd9be3f3397358648c94","amount":2.5,"unit":"pi\u00e8ce"},{"id":"5c8bcd9de3f33973480ec962","amount":2.5,"unit":"pi\u00e8ce"},{"id":"5c70001ce3f3396c4723f663","amount":25,"unit":"g"},{"id":"5af2be04ae08b5194415a151","amount":50,"unit":"g"},{"id":"5c950d77c445fa28926e8832","amount":2.5,"unit":"pi\u00e8ce"},{"id":"5bdc60dbae08b57bc06363d5","amount":5,"unit":"pi\u00e8ce"},{"id":"5af2be68ae08b5194415a2c0","amount":2.5,"unit":"pi\u00e8ce"},{"id":"5bceef3a30006c2b0d5d7232","amount":1.25,"unit":"bo\u00eete(s)"},{"id":"5af2be60ae08b5194415a2a2","amount":500,"unit":"g"},{"id":"5ca75c90e3f339258a36e9f2","amount":10,"unit":"cs"},{"id":"5c8bcd9be3f3397358648c92","amount":2.5,"unit":"cs"},{"id":"5c8bcd9ce3f3397358648c95","amount":2.5,"unit":"cs"},{"id":"5c8bcdafe3f3397358648c99","amount":250,"unit":"ml"},{"id":"5c8bcd9be3f3397358648c93","amount":null,"unit":"selon le go\u00fbt"}]},{"yields":6,"ingredients":[{"id":"5c8bcd9be3f3397358648c94","amount":3,"unit":"pi\u00e8ce"},{"id":"5c8bcd9de3f33973480ec962","amount":3,"unit":"pi\u00e8ce"},{"id":"5c70001ce3f3396c4723f663","amount":30,"unit":"g"},{"id":"5af2be04ae08b5194415a151","amount":60,"unit":"g"},{"id":"5c950d77c445fa28926e8832","amount":3,"unit":"pi\u00e8ce"},{"id":"5bdc60dbae08b57bc06363d5","amount":6,"unit":"pi\u00e8ce"},{"id":"5af2be68ae08b5194415a2c0","amount":3,"unit":"pi\u00e8ce"},{"id":"5bceef3a30006c2b0d5d7232","amount":1.5,"unit":"bo\u00eete(s)"},{"id":"5af2be60ae08b5194415a2a2","amount":600,"unit":"g"},{"id":"5ca75c90e3f339258a36e9f2","amount":12,"unit":"cs"},{"id":"5c8bcd9be3f3397358648c92","amount":3,"unit":"cs"},{"id":"5c8bcd9ce3f3397358648c95","amount":3,"unit":"cs"},{"id":"5c8bcdafe3f3397358648c99","amount":300,"unit":"ml"},{"id":"5c8bcd9be3f3397358648c93","amount":null,"unit":"selon le go\u00fbt"}]}],"steps":[{"index":1,"instructionsMarkdown":"Pr\u00e9parez le bouillon dans un bol avec de l'eau chaude. \u00c9mincez l'\u00e9chalote. Pressez ou \u00e9mincez l'ail. Ciselez le persil, le basilic et la menthe fra\u00eeche. Hachez les c\u00e2pres. Coupez le citron en quartiers.","instructionsHTML":"<p>Pr\u00e9parez le bouillon dans un bol avec de l'eau chaude. \u00c9mincez l'\u00e9chalote. Pressez ou \u00e9mincez l'ail. Ciselez le persil, le basilic et la menthe fra\u00eeche. Hachez les c\u00e2pres. Coupez le citron en quartiers.<\/p>","instructions":"Pr\u00e9parez le bouillon dans un bol avec de l'eau chaude. \u00c9mincez l'\u00e9chalote. Pressez ou \u00e9mincez l'ail. Ciselez le persil, le basilic et la menthe fra\u00eeche. Hachez les c\u00e2pres. Coupez le citron en quartiers.","timers":[],"images":[{"link":"https:\/\/d3hvwccx09j84u.cloudfront.net\/0,0\/5ee9f900a07cac1a3c56ad21\/step-f61a7245.jpg","path":"\/5ee9f900a07cac1a3c56ad21\/step-f61a7245.jpg","caption":"Pr\u00e9parer"}],"videos":[],"ingredients":["5c70001ce3f3396c4723f663","5af2be04ae08b5194415a151","5c8bcd9de3f33973480ec962","5c950d77c445fa28926e8832","5c8bcdafe3f3397358648c99","5c8bcd9be3f3397358648c94"],"utensils":["57e2674fb7e8697d4b305369"]},{"index":2,"instructionsMarkdown":"M\u00e9langez dans un petit bol l'huile d'olive, la moiti\u00e9 de l'\u00e9chalote, l'ail, le m\u00e9lange d'herbes aromatiques et les c\u00e2pres. Salez et poivrez puis m\u00e9langez. Ajoutez quelques gouttes de jus de citron selon votre go\u00fbt.","instructionsHTML":"<p>M\u00e9langez dans un petit bol l'huile d'olive, la moiti\u00e9 de l'\u00e9chalote, l'ail, le m\u00e9lange d'herbes aromatiques et les c\u00e2pres. Salez et poivrez puis m\u00e9langez. Ajoutez quelques gouttes de jus de citron selon votre go\u00fbt.<\/p>","instructions":"M\u00e9langez dans un petit bol l'huile d'olive, la moiti\u00e9 de l'\u00e9chalote, l'ail, le m\u00e9lange d'herbes aromatiques et les c\u00e2pres. Salez et poivrez puis m\u00e9langez. Ajoutez quelques gouttes de jus de citron selon votre go\u00fbt.","timers":[],"images":[{"link":"https:\/\/d3hvwccx09j84u.cloudfront.net\/0,0\/5ee9f900a07cac1a3c56ad21\/step-d60e8ea1.jpg","path":"\/5ee9f900a07cac1a3c56ad21\/step-d60e8ea1.jpg","caption":"Faire la salsa"}],"videos":[],"ingredients":["5c8bcd9be3f3397358648c93","5ca75c90e3f339258a36e9f2"],"utensils":["57e2674fb7e8697d4b305380"]},{"index":3,"instructionsMarkdown":"Salez et poivrez la viande des deux c\u00f4t\u00e9s. Faites chauffer 1\/2 cs d'huile d'olive et de beurre par personne dans une sauteuse \u00e0 feu vif. Ajoutez les c\u00f4tes de porc et faites-les dorer 2 \u00e0 3 minutes sans les bouger. Retournez-les et prolongez la cuisson jusqu'\u00e0 ce que la viande soit \u00e0 peine cuite, environ 3 minutes de plus. Retirez la viande et d\u00e9posez-la sur une assiette recouverte de papier d'aluminium. Laissez reposer.","instructionsHTML":"<p>Salez et poivrez la viande des deux c\u00f4t\u00e9s. Faites chauffer 1\/2 cs d'huile d'olive et de beurre par personne dans une sauteuse \u00e0 feu vif. Ajoutez les c\u00f4tes de porc et faites-les dorer 2 \u00e0 3 minutes sans les bouger. Retournez-les et prolongez la cuisson jusqu'\u00e0 ce que la viande soit \u00e0 peine cuite, environ 3 minutes de plus. Retirez la viande et d\u00e9posez-la sur une assiette recouverte de papier d'aluminium. Laissez reposer.<\/p>","instructions":"Salez et poivrez la viande des deux c\u00f4t\u00e9s. Faites chauffer 1\/2 cs d'huile d'olive et de beurre par personne dans une sauteuse \u00e0 feu vif. Ajoutez les c\u00f4tes de porc et faites-les dorer 2 \u00e0 3 minutes sans les bouger. Retournez-les et prolongez la cuisson jusqu'\u00e0 ce que la viande soit \u00e0 peine cuite, environ 3 minutes de plus. Retirez la viande et d\u00e9posez-la sur une assiette recouverte de papier d'aluminium. Laissez reposer.","timers":[{"name":"Cuire la viande d'un c\u00f4t\u00e9","duration":"PT03M","temperature":null,"temperatureUnit":null,"ovenMode":null},{"name":"Retouner et prolonger la cuisson","duration":"PT03M","temperature":null,"temperatureUnit":null,"ovenMode":null}],"images":[{"link":"https:\/\/d3hvwccx09j84u.cloudfront.net\/0,0\/5ee9f900a07cac1a3c56ad21\/step-2e027387.jpg","path":"\/5ee9f900a07cac1a3c56ad21\/step-2e027387.jpg","caption":"Cuire la viande"}],"videos":[],"ingredients":["5bdc60dbae08b57bc06363d5","5c8bcd9be3f3397358648c93","5c8bcd9be3f3397358648c92","5c8bcd9ce3f3397358648c95"],"utensils":["57e2674fb7e8697d4b305366","57e2674fb7e8697d4b305389"]},{"index":4,"instructionsMarkdown":"Pendant ce temps, \u00e9pluchez la carotte et \u00e0 l'aide de l'\u00e9plucheur, taillez-la en longs rubans.","instructionsHTML":"<p>Pendant ce temps, \u00e9pluchez la carotte et \u00e0 l'aide de l'\u00e9plucheur, taillez-la en longs rubans.<\/p>","instructions":"Pendant ce temps, \u00e9pluchez la carotte et \u00e0 l'aide de l'\u00e9plucheur, taillez-la en longs rubans.","timers":[],"images":[{"link":"https:\/\/d3hvwccx09j84u.cloudfront.net\/0,0\/5ee9f900a07cac1a3c56ad21\/step-0ec3b545.jpg","path":"\/5ee9f900a07cac1a3c56ad21\/step-0ec3b545.jpg","caption":"Rubans de carotte"}],"videos":[],"ingredients":["5af2be68ae08b5194415a2c0"],"utensils":["57e2674fb7e8697d4b305379"]},{"index":5,"instructionsMarkdown":"Remettez la m\u00eame sauteuse \u00e0 feu moyen-vif et faites revenir le reste d'\u00e9chalote dans la graisse de cuisson 1 minute. Ajoutez les rubans de carotte, les haricots et le bouillon. Faites cuire \u00e0 feu moyen-vif, en remuant souvent, jusqu'\u00e0 ce que le tout soit chaud, environ 2 minutes. Ajoutez les \u00e9pinards et remuez encore 2 minutes jusqu'\u00e0 ce qu'ils soient juste fan\u00e9s.","instructionsHTML":"<p>Remettez la m\u00eame sauteuse \u00e0 feu moyen-vif et faites revenir le reste d'\u00e9chalote dans la graisse de cuisson 1 minute. Ajoutez les rubans de carotte, les haricots et le bouillon. Faites cuire \u00e0 feu moyen-vif, en remuant souvent, jusqu'\u00e0 ce que le tout soit chaud, environ 2 minutes. Ajoutez les \u00e9pinards et remuez encore 2 minutes jusqu'\u00e0 ce qu'ils soient juste fan\u00e9s.<\/p>","instructions":"Remettez la m\u00eame sauteuse \u00e0 feu moyen-vif et faites revenir le reste d'\u00e9chalote dans la graisse de cuisson 1 minute. Ajoutez les rubans de carotte, les haricots et le bouillon. Faites cuire \u00e0 feu moyen-vif, en remuant souvent, jusqu'\u00e0 ce que le tout soit chaud, environ 2 minutes. Ajoutez les \u00e9pinards et remuez encore 2 minutes jusqu'\u00e0 ce qu'ils soient juste fan\u00e9s.","timers":[{"name":"Faire revenir l'\u00e9chalote","duration":"PT01M","temperature":null,"temperatureUnit":null,"ovenMode":null},{"name":"Cuire les l\u00e9gumes sans  les \u00e9pinards","duration":"PT02M","temperature":null,"temperatureUnit":null,"ovenMode":null},{"name":"Ajouter les \u00e9pinards et prolonger la cuisson","duration":"PT02M","temperature":null,"temperatureUnit":null,"ovenMode":null}],"images":[{"link":"https:\/\/d3hvwccx09j84u.cloudfront.net\/0,0\/5ee9f900a07cac1a3c56ad21\/step-59f35d7e.jpg","path":"\/5ee9f900a07cac1a3c56ad21\/step-59f35d7e.jpg","caption":"Cuire les l\u00e9gumes"}],"videos":[],"ingredients":["5bceef3a30006c2b0d5d7232","5af2be60ae08b5194415a2a2","5c8bcdafe3f3397358648c99"],"utensils":[]},{"index":6,"instructionsMarkdown":"V\u00e9rifiez l'assaisonnement et servez les l\u00e9gumes avec les c\u00f4tes de porc en garnissant de salsa verde et des quartiers de citron.","instructionsHTML":"<p>V\u00e9rifiez l'assaisonnement et servez les l\u00e9gumes avec les c\u00f4tes de porc en garnissant de salsa verde et des quartiers de citron.<\/p>","instructions":"V\u00e9rifiez l'assaisonnement et servez les l\u00e9gumes avec les c\u00f4tes de porc en garnissant de salsa verde et des quartiers de citron.","timers":[],"images":[{"link":"https:\/\/d3hvwccx09j84u.cloudfront.net\/0,0\/5ee9f900a07cac1a3c56ad21\/step-8e7bd872.jpg","path":"\/5ee9f900a07cac1a3c56ad21\/step-8e7bd872.jpg","caption":"Servir"}],"videos":[],"ingredients":["5c8bcd9be3f3397358648c93"],"utensils":[]}],"wines":[],"marketplaceItems":[],"author":"family","label":null,"yieldType":"servings","averageRating":3,"ratingsCount":49,"favoritesCount":69,"active":true,"highlighted":false,"isDinnerToLunch":false,"isExcludedFromIndex":false,"isAddon":false,"isPremium":false,"websiteUrl":"https:\/\/www.hellofresh.fr\/recipes\/cote-de-porc-dans-lechine-salsa-verde-italienne-5ee9f900a07cac1a3c56ad21","clonedFrom":null,"canonical":null,"canonicalLink":null,"promotion":null,"uniqueRecipeCode":null,"uuid":null}